smart_data_manager/__init__.py
smart_data_manager/clean.py
smart_data_manager/daily_sales_etl.py
smart_data_manager/db.py
smart_data_manager/extract.py
smart_data_manager/load.py
smart_data_manager/rds_db.py
smart_data_manager/run_etl_pipeline.py
smart_data_manager/schema.sql
smart_data_manager/seed.py
smart_data_manager/seed.sql
smart_data_manager/test_connection.py
smart_data_manager/transform.py
smart_data_manager-1.0.18.dist-info/METADATA
smart_data_manager-1.0.18.dist-info/WHEEL
smart_data_manager-1.0.18.dist-info/top_level.txt
smart_data_manager-1.0.18.dist-info/RECORD
