Metadata-Version: 2.4
Name: smart-data-manager
Version: 1.0.18
Summary: ETL logic for Smart Data Manager.
Author: Sinomtha Mzamo
Requires-Dist: pandas>=2.2
Requires-Dist: SQLAlchemy>=2.0
Requires-Dist: pyodbc>=5.1
Dynamic: author
Dynamic: description
Dynamic: description-content-type
Dynamic: requires-dist
Dynamic: summary
